d43_aws_tools/__init__.py
d43_aws_tools/dynamodb_handler.py
d43_aws_tools/s3_handler.py
d43_aws_tools/ses_handler.py
d43_aws_tools-1.0.4.dist-info/top_level.txt
d43_aws_tools-1.0.4.dist-info/METADATA
d43_aws_tools-1.0.4.dist-info/DESCRIPTION.rst
d43_aws_tools-1.0.4.dist-info/metadata.json
d43_aws_tools-1.0.4.dist-info/WHEEL
d43_aws_tools-1.0.4.dist-info/RECORD
