Metadata-Version: 2.0
Name: d43-aws-tools
Version: 1.0.4
Summary: Classes for accessing AWS APIs
Home-page: https://github.org/unfoldingWord-dev/python-aws-tools
Author: unfoldingWord
Author-email: info@unfoldingword.org
License: MIT
Keywords: aws tools,unfoldingword,lambda
Platform: UNKNOWN
Classifier: License :: OSI Approved :: MIT License
Classifier: Programming Language :: Python :: 2.7
Requires-Dist: boto3 (==1.4.4)
Requires-Dist: moto (==1.0.1)
Requires-Dist: mock (==2.0.0)
